tagesschauscraper/__init__.py
tagesschauscraper/constants.py
tagesschauscraper/helper.py
tagesschauscraper/retrieve.py
tagesschauscraper/tagesschau.py
tagesschauscraper-0.1.2.dist-info/LICENSE
tagesschauscraper-0.1.2.dist-info/METADATA
tagesschauscraper-0.1.2.dist-info/WHEEL
tagesschauscraper-0.1.2.dist-info/top_level.txt
tagesschauscraper-0.1.2.dist-info/RECORD
