Metadata-Version: 2.1
Name: tagesschauscraper
Version: 0.1.2
Summary: A library for scraping the German news archive of Tagesschau.de
Home-page: https://github.com/TheFerry10/TagesschauScraper
Author: Malte Sauerwein
Author-email: malte.sauerwein@live.de
License: GPL-3.0 license
Project-URL: Bug Reports, https://github.com/TheFerry10/tagesschauscraper/issues
Project-URL: Source, https://github.com/TheFerry10/tagesschauscraper
Keywords: tagesschau scraper scraping news archive
Platform: UNKNOWN
Requires-Dist: beautifulsoup4 (==4.11.1)
Requires-Dist: requests (==2.28.2)
